Metadata-Version: 2.1
Name: pycat3
Version: 0.6
Summary: Python Beckhoff communication over ads
Home-page: UNKNOWN
Author: Sofian Hanash
Author-email: soha@kea.dk
License: MIT
Keywords: python,beackhoff,ads
Platform: UNKNOWN
Classifier: Programming Language :: Python :: 3
Classifier: Operating System :: Microsoft :: Windows
Classifier: Operating System :: MacOS :: MacOS X
Classifier: Operating System :: Unix
License-File: LICENSE.txt
